dougrain_forms/mixin.py
dougrain_forms/form.py
dougrain_forms/_version.py
dougrain_forms/__init__.py
dougrain_forms-0.0.3.data/data/README.rst
dougrain_forms-0.0.3.dist-info/top_level.txt
dougrain_forms-0.0.3.dist-info/METADATA
dougrain_forms-0.0.3.dist-info/metadata.json
dougrain_forms-0.0.3.dist-info/WHEEL
dougrain_forms-0.0.3.dist-info/RECORD
