Metadata-Version: 2.0
Name: dougrain-forms
Version: 0.0.3
Summary: Unofficial hypermedia form extension for dougrain.
Home-page: https://github.com/weluse/dougrain-forms
Author: Pascal Hartig
Author-email: phartig@weluse.de
License: BSD
Platform: UNKNOWN
Classifier: Development Status :: 3 - Alpha
Classifier: Intended Audience :: Developers
Classifier: License :: OSI Approved :: BSD License
Classifier: Operating System :: POSIX
Classifier: Programming Language :: Python
Classifier: Topic :: Internet :: WWW/HTTP
Classifier: Topic :: Software Development :: Libraries :: Python Modules
Requires-Dist: dougrain (==0.4)
